{
  "creds": {
    "noiseKey": {
      "private": {
        "type": "Buffer",
        "data": "YMZld0zLicGGrG8zkM95445atlMS35Z+Ccs2c9WYRHQ="
      },
      "public": {
        "type": "Buffer",
        "data": "1Lut/P7OPUNVv2zU9NBx7I7Gz4cpTZEewtxWkBZMh3g="
      }
    },
    "signedIdentityKey": {
      "private": {
        "type": "Buffer",
        "data": "sIyvv0tQ4QhXlZ/FU9rPAvsz0JB7PiFU15j4LtXngUo="
      },
      "public": {
        "type": "Buffer",
        "data": "RvFyci+n1C6gHYP56LtDiKkEHL5Y9Wo9uTPliY5BhQc="
      }
    },
    "signedPreKey": {
      "keyPair": {
        "private": {
          "type": "Buffer",
          "data": "uC+NDZ454pYRBPXGUa/4fPPVDzgygxR1kzbM2oCPkF4="
        },
        "public": {
          "type": "Buffer",
          "data": "W9pegNP697P5gAvl0KQM7ingVwZ7xL4k4sHP37OjRUA="
        }
      },
      "signature": {
        "type": "Buffer",
        "data": "mq7Gh97NqhjP2tQB2Kmr44wcVD5C4RdbBiEMqz4swxdN0kwk99jMIHiK+B/iHvKUDYRSwJWhWAOK34r6TRh2gA=="
      },
      "keyId": 1
    },
    "registrationId": 155,
    "advSecretKey": "Vt76xatyCokhU12UratR0YU2kNdKybcUFj/3y6j4A4c=",
    "processedHistoryMessages": [
      {
        "key": {
          "remoteJid": "14373742193@s.whatsapp.net",
          "fromMe": true,
          "id": "9E1B99ED3E120FD3072774D47708E59A"
        },
        "messageTimestamp": 1664526328
      },
      {
        "key": {
          "remoteJid": "14373742193@s.whatsapp.net",
          "fromMe": true,
          "id": "81DF367AD6ECB8A55CCB4FA65BA37788"
        },
        "messageTimestamp": 1664526328
      },
      {
        "key": {
          "remoteJid": "14373742193@s.whatsapp.net",
          "fromMe": true,
          "id": "81A3EB131E765140D4A331B9524DC0D3"
        },
        "messageTimestamp": 1664526334
      }
    ],
    "nextPreKeyId": 31,
    "firstUnuploadedPreKeyId": 31,
    "accountSettings": {
      "unarchiveChats": false
    },
    "account": {
      "details": "CLbJno4BEPLP2pkGGAE=",
      "accountSignatureKey": "N1sSfk+hySk1BYx8K2jcQcOVy3t8xjzoxFWPAmAcNjc=",
      "accountSignature": "n+KmXVGeJoYvaeFRGZt9SrNw/pK2XUxSzf5lshimsCyOIuEIf6P6Yey5gxhuhCortalhUnQOpKtS4lAeygt5Cw==",
      "deviceSignature": "xSFnMzzhAHYuSTAtUv+sT3ybQCc9LGWWpNv2XNqKknjgsN+rUoOYjWPrQi/DKMRJseo1wiyYbGR1pau55KnSjA=="
    },
    "me": {
      "id": "14373742193:1@s.whatsapp.net",
      "name": "Korio"
    },
    "signalIdentities": [
      {
        "identifier": {
          "name": "14373742193:1@s.whatsapp.net",
          "deviceId": 0
        },
        "identifierKey": {
          "type": "Buffer",
          "data": "BTdbEn5PockpNQWMfCto3EHDlct7fMY86MRVjwJgHDY3"
        }
      }
    ],
    "platform": "android",
    "lastAccountSyncTimestamp": 1664526325,
    "myAppStateKeyId": "AAAAALzX"
  },
  "keys": {
    "preKeys": {
      "1": {
        "private": {
          "type": "Buffer",
          "data": "sKN0FiOtGJ0RMFFTZyuIz6VMEsy3uGPubfZkY61bGGg="
        },
        "public": {
          "type": "Buffer",
          "data": "0DLrxdxgEtTMc/zXrTYCmha+Ox4xAq5aJ+Gdiw1vCBg="
        }
      },
      "2": {
        "private": {
          "type": "Buffer",
          "data": "oAXmi3rK3T+pvsuzjl9w9J/ASp3j5AURqDOx4z1QkHM="
        },
        "public": {
          "type": "Buffer",
          "data": "3BDpcXZ8/b2Gc0X1Gg0NfvYJ1zQ//uUqXIejkzbvhV8="
        }
      },
      "3": {
        "private": {
          "type": "Buffer",
          "data": "kIwS/EFuuZkpHc1BOqseP9sEwTmF6DRf+kZvjxBCs3w="
        },
        "public": {
          "type": "Buffer",
          "data": "yjB9q+zt9Rz4AGbvFD4goaincA4oMt1SGIi6rmGCqRs="
        }
      },
      "4": {
        "private": {
          "type": "Buffer",
          "data": "cBPrYEFuCPJFa4KI8TQCJWrRc11DnaqUk1HlKplNR3k="
        },
        "public": {
          "type": "Buffer",
          "data": "Y7YXw7tS1fuUjMIkI3CrKbGw6BflP3+rKcsqZXqv3mg="
        }
      },
      "5": {
        "private": {
          "type": "Buffer",
          "data": "mM5LrYex5zvVop1oRYNCEIwhMBsEF/x4riW0Tj+btU0="
        },
        "public": {
          "type": "Buffer",
          "data": "F/mWEWu7TV6JkGW2C9VXZqop1dMKvxN2Yb5+uFebW28="
        }
      },
      "6": {
        "private": {
          "type": "Buffer",
          "data": "4K7EpToWMP3OArVxnZwLJS8Va2LsLNcbJ9NF6tFD10Y="
        },
        "public": {
          "type": "Buffer",
          "data": "jzzFpTdr1mP+94Ease0ly9DeGL6qv0521bMscMPFbXw="
        }
      },
      "7": {
        "private": {
          "type": "Buffer",
          "data": "cHgUpvJqewjab+N3oeB8tFcnO2OJnidS53g65sD52m0="
        },
        "public": {
          "type": "Buffer",
          "data": "EN+YWS0V5t/NNfya3FO2L/KqRBVCFOaCVZ9imdkqJyo="
        }
      },
      "8": {
        "private": {
          "type": "Buffer",
          "data": "yOIiNuKryqmazKU2qgMPNWJQY3bUswtCiXfOaBzd3V8="
        },
        "public": {
          "type": "Buffer",
          "data": "pv4T1T5TXBWqqqKZGctTPDdkJUF72G1v2l9GKM9XOQs="
        }
      },
      "9": {
        "private": {
          "type": "Buffer",
          "data": "oGnRXq+mPRoYeoGjyUst/WRAp5TBjRaDpOYL/NAZ5nY="
        },
        "public": {
          "type": "Buffer",
          "data": "w8P9fl+f2zgDNZCPIrnRFZAbCqtndp0c/U+sSDZ7bnw="
        }
      },
      "10": {
        "private": {
          "type": "Buffer",
          "data": "qJRKAGD+MnxJeiMhWHDUXNQy7CAlI4dKd60NyNGBzXw="
        },
        "public": {
          "type": "Buffer",
          "data": "dzcXQjyb8BVFYyrnJNo+vZ466GTAROGfJfB1dk5WmRo="
        }
      },
      "11": {
        "private": {
          "type": "Buffer",
          "data": "AELwlIpyzvOcUsqnuxc83tJlVWYa+Pw0CjMdjip9PWE="
        },
        "public": {
          "type": "Buffer",
          "data": "+dlAcD3ni2HmOAtbWYuSjjX+/rAl5CNZ7K8Y9P5VYE4="
        }
      },
      "12": {
        "private": {
          "type": "Buffer",
          "data": "OKWjtc/lWYJdn0NavAeiqjE8C4JsWT3RdoAZisIPdkg="
        },
        "public": {
          "type": "Buffer",
          "data": "pxNQDFLCFM5bQ9gly25423UOrzhRbgikJ0bBmPoYGFg="
        }
      },
      "13": {
        "private": {
          "type": "Buffer",
          "data": "0FlwNqveXRmeWAz9JBYjNtpReTciuA7N7Ia+WKIQ5E4="
        },
        "public": {
          "type": "Buffer",
          "data": "TalpLqRpBfgm+ISZ8qlyEQHv4jOUq74RcaU0Ab7GTWY="
        }
      },
      "14": {
        "private": {
          "type": "Buffer",
          "data": "uNOwEYmmzUwmYslOrqmn9/5WP46Z524CZdwagKy7ymM="
        },
        "public": {
          "type": "Buffer",
          "data": "U3kFW224gUEqxpT7VoTdm9ZXkiQqUF3HXDPa4MiHGVg="
        }
      },
      "15": {
        "private": {
          "type": "Buffer",
          "data": "kPob2UiMCwmcKfpwlApHzkmGCIPvcsp4LOadQg+c83I="
        },
        "public": {
          "type": "Buffer",
          "data": "h3ZTF7ONeML4sN+nNZTomN7vi2RDglp62PYoEsNs0Bc="
        }
      },
      "16": {
        "private": {
          "type": "Buffer",
          "data": "8LYhCyro/nP7d5PT3oXNwvKWzhNhD3XyZNMHlXNej38="
        },
        "public": {
          "type": "Buffer",
          "data": "bz5LlZoqZmOEoTDh0Y0ylNhFUow4hhkyFvgUiZFToBQ="
        }
      },
      "17": {
        "private": {
          "type": "Buffer",
          "data": "UN/EUB1Fg3l5ymFg1rRR4KIF7741XxDb04v1bmJl62Y="
        },
        "public": {
          "type": "Buffer",
          "data": "bpMInxD+Wf6OAbCzYafkg5iqlt8G2/ha2IwHmV+Csm0="
        }
      },
      "18": {
        "private": {
          "type": "Buffer",
          "data": "mBZpsIFDBuOC5Q/J5dhOjrKYG5VZ8L+J4QMQWKKjzEA="
        },
        "public": {
          "type": "Buffer",
          "data": "VOKk4sNU4pFcHHzkAHap3I0OUuRh1shUOKHsi/94pGQ="
        }
      },
      "19": {
        "private": {
          "type": "Buffer",
          "data": "8N9dWO/onqnKptcxD24qm7b+MfvJ6s6pa8h72ZSqVVc="
        },
        "public": {
          "type": "Buffer",
          "data": "uouxGLRKfzmtKeFjKH8ecZPz/93QfkMZC/1kdOdf6Hk="
        }
      },
      "20": {
        "private": {
          "type": "Buffer",
          "data": "2EhXPyTbai1xzb8YmuHsx+wYnYWbmF9pq0/FM/QykFY="
        },
        "public": {
          "type": "Buffer",
          "data": "UB4Gg/F9ebd3ZGlnA6o5Obo/wWbhcgIsQ1HuWY8TVmo="
        }
      },
      "21": {
        "private": {
          "type": "Buffer",
          "data": "OJijKgCulVOFqwBdqeMHkhjHIFL7gVOUTQUgcshGH1o="
        },
        "public": {
          "type": "Buffer",
          "data": "Fzl7Yz3Vr+WyxHGL8jFgxoLjP4buPpyStErm8RRarH4="
        }
      },
      "22": {
        "private": {
          "type": "Buffer",
          "data": "kEjgAsKdUSmbQ0jPV6MoFhRhL3MiHx6R/eAjvvf9vn0="
        },
        "public": {
          "type": "Buffer",
          "data": "CK+I7NB5/t9VUPi+HtTBw9zCBLrOFVzsrqbCoLejWxA="
        }
      },
      "23": {
        "private": {
          "type": "Buffer",
          "data": "6JcqYyTpcG0ybFsp9VWxumdMOi66a99lLyxsbI4kw3Y="
        },
        "public": {
          "type": "Buffer",
          "data": "3CO9KHioTZ5RLwYaQYDGUiFgL8303hfRsB53Mh/d/HE="
        }
      },
      "24": null,
      "25": {
        "private": {
          "type": "Buffer",
          "data": "qMPUpK7MxQNFWuHM934Ii3+7zg6ARHM53dO+no+d1kA="
        },
        "public": {
          "type": "Buffer",
          "data": "LO6vZ4ra6CQ8OwiouBnfA4f9dJ1o8YAxl6QxmZgnHjs="
        }
      },
      "26": {
        "private": {
          "type": "Buffer",
          "data": "EJPAq7eyxx9EqbuC9C4i+apP331byUhYP434+A2t7Wo="
        },
        "public": {
          "type": "Buffer",
          "data": "lckxmuTDPUDXXCBCaSvW+JmmFVjU/e6iEh2Bm7Q/y2I="
        }
      },
      "27": {
        "private": {
          "type": "Buffer",
          "data": "QOrbp2r3PBMXDCs+iqidE7rMWsoFDSGO2uS9osN4KnY="
        },
        "public": {
          "type": "Buffer",
          "data": "n5Sd35Ose8ZoVrUaLeb5bmnPFrgWsuCWKO6VPIKwVQw="
        }
      },
      "28": {
        "private": {
          "type": "Buffer",
          "data": "kEVhi9USe9ya1NgA7uCYwmOEmqzsgV8MtPGRzH/80nI="
        },
        "public": {
          "type": "Buffer",
          "data": "Duylvy0eQGiHdvhy6DEUBzjjHOTsNOQEGRnsdhIxTxs="
        }
      },
      "29": {
        "private": {
          "type": "Buffer",
          "data": "oLvFF1QgeOHlHiIMRfHin2jtpSM8E+4U5WddBI/SxEc="
        },
        "public": {
          "type": "Buffer",
          "data": "uzS+ixHpkC1aTN7nKvs3JeAVDLQetUWuIFT2TQSBuC4="
        }
      },
      "30": {
        "private": {
          "type": "Buffer",
          "data": "sPj7gTD8GPYM0XjuQen5DehG2g1WM8ZYlZjr9sL561A="
        },
        "public": {
          "type": "Buffer",
          "data": "k+0+QLfc+j/DYlz+k9d5WcKGlB9bBMY16w2OP/M8ZHU="
        }
      }
    },
    "sessions": {
      "14373742193.0": {
        "_sessions": {
          "BTyX8lDzi2UeDzc09RhxmMiucNfj2ySkL76LLxdNgDYv": {
            "registrationId": 1695836909,
            "currentRatchet": {
              "ephemeralKeyPair": {
                "pubKey": "Bb9SMZHGB0tS5YhuQDcHejt/GSDrEQDcQHiYzSjXbyl7",
                "privKey": "8FJ6Opj/JN8iDklyzkacCccLqpCBCG4S8ukktIeHIm0="
              },
              "lastRemoteEphemeralKey": "BZMLk6FX51MZVpN+fY4keMTNSpqTOb0KuFEBj4yLUU9R",
              "previousCounter": 0,
              "rootKey": "06j98W6/4ylFG8cDI34gQBxV+cAMS+kokWx8Lk7vD5I="
            },
            "indexInfo": {
              "baseKey": "BTyX8lDzi2UeDzc09RhxmMiucNfj2ySkL76LLxdNgDYv",
              "baseKeyType": 2,
              "closed": -1,
              "used": 1664526326195,
              "created": 1664526326195,
              "remoteIdentityKey": "BTdbEn5PockpNQWMfCto3EHDlct7fMY86MRVjwJgHDY3"
            },
            "_chains": {
              "BZMLk6FX51MZVpN+fY4keMTNSpqTOb0KuFEBj4yLUU9R": {
                "chainKey": {
                  "counter": 7,
                  "key": "vHUqhqvOSqkzYuUHhEFNQUglhu0n0v84gZtyo4G/Tx0="
                },
                "chainType": 2,
                "messageKeys": {}
              },
              "Bb9SMZHGB0tS5YhuQDcHejt/GSDrEQDcQHiYzSjXbyl7": {
                "chainKey": {
                  "counter": 1,
                  "key": "9Ko4kgcANwvLDcPBzsoY5Ls3JtxrfopWLV7Igc4hluI="
                },
                "chainType": 1,
                "messageKeys": {}
              }
            }
          }
        },
        "version": "v1"
      }
    },
    "appStateSyncKeys": {
      "AAAAALzX": {
        "keyData": "8S0oF1HZw7MQ7RwFhZjkH8ZHzP6tukhHYs2Q0znL8iM=",
        "fingerprint": {
          "rawId": 298296502,
          "currentIndex": 1,
          "deviceIndexes": [
            0,
            1
          ]
        },
        "timestamp": "1664526326647"
      }
    },
    "appStateVersions": {
      "critical_block": {
        "version": 1,
        "hash": {
          "type": "Buffer",
          "data": "LsbR7aJTs2I4NSoqcCjUSrMdyVJlO1ygY9kEbIN9yhE0qWMSNdL4SYGB44PBjfaLgEV3Nu5SpY85l086leookr000alJ+j+mbr2dTUP78frwHqKfqfEUg0RXZuAmEZpG75fIupNYv9Dzai3Ufr8jfSyrIRp4Tub9/5/1GG9BiZ0="
        },
        "indexValueMap": {
          "WSLc7dS+NjwCf4ilh8ja8X5iY4KOBSdyEJGrrtjr1kU=": {
            "valueMac": {
              "type": "Buffer",
              "data": "e+rMdN3s2ngdW6gbckcCuoquDOt/g/4bhskHtd2OL+4="
            }
          },
          "vXGkg8YUcE0GGpW1gRAFlxLPZ84OLph2Pd3t0PNU4ng=": {
            "valueMac": {
              "type": "Buffer",
              "data": "de6ygvvjWMTMDyFTxnjdlKdB7OsgGCLB0KqbiuIjXkA="
            }
          }
        }
      },
      "regular": {
        "version": 1,
        "hash": {
          "type": "Buffer",
          "data": "V7VKGqzIY0MsO5qiP/pLtLJmp7CBdURa345BHZyovBIstFf8pxs+PEGqu9t8zv6mV3Ah3o+gzJaxDdaUOfKySQ2cP3KcZiuVXdjRo9qEx4A7WvdWWqj0NMEopXDxuc84rQw4dpWdi+CF78u6qFbAXGZ598pr6FH+Y6ZBlfsbbaU="
        },
        "indexValueMap": {
          "2E3JAfLINoGdSvUOB95ZyiiIl9R6t5FPi3o/0HQwFtM=": {
            "valueMac": {
              "type": "Buffer",
              "data": "dBSLzs34yKN7LY8mXOrf5ky3V9o1V4AKGbceLgRdwyU="
            }
          }
        }
      }
    }
  }
}
